mem0_agent_memory/__init__.py
mem0_agent_memory/__main__.py
mem0_agent_memory/bedrock_patch.py
mem0_agent_memory/server.py
mem0_agent_memory/docs/AGENT_GUIDANCE.md
mem0_agent_memory-1.3.2.dist-info/licenses/LICENSE
mem0_agent_memory-1.3.2.dist-info/METADATA
mem0_agent_memory-1.3.2.dist-info/WHEEL
mem0_agent_memory-1.3.2.dist-info/entry_points.txt
mem0_agent_memory-1.3.2.dist-info/top_level.txt
mem0_agent_memory-1.3.2.dist-info/RECORD
