Metadata-Version: 2.4
Name: mem0-agent-memory
Version: 1.3.2
Summary: MCP server for Mem0 agent memory management with multi-backend support
Author-email: Arunkumar Selvam <aruninfy123@gmail.com>
License: MIT
Project-URL: Homepage, https://github.com/arunkumars-mf/mem0-agent-memory
Project-URL: Bug Reports, https://github.com/arunkumars-mf/mem0-agent-memory/issues
Project-URL: Source, https://github.com/arunkumars-mf/mem0-agent-memory
Project-URL: Citation, https://github.com/arunkumars-mf/mem0-agent-memory/blob/main/CITATION.cff
Keywords: mem0,mcp,memory,ai,agent,vector-search,faiss,qdrant,opensearch
Classifier: Development Status :: 5 - Production/Stable
Classifier: Intended Audience :: Developers
Classifier: License :: OSI Approved :: MIT License
Classifier: Topic :: Software Development :: Libraries :: Python Modules
Classifier: Topic :: Scientific/Engineering :: Artificial Intelligence
Classifier: Programming Language :: Python :: 3
Classifier: Programming Language :: Python :: 3.11
Classifier: Programming Language :: Python :: 3.12
Classifier: Programming Language :: Python :: 3.13
Requires-Python: >=3.11
License-File: LICENSE
Requires-Dist: mcp>=1.13.0
Requires-Dist: fastmcp>=2.11.0
Requires-Dist: mem0ai>=1.0.0
Requires-Dist: boto3>=1.40.0
Requires-Dist: opensearch-py>=3.0.0
Requires-Dist: faiss-cpu>=1.12.0
Requires-Dist: qdrant-client>=1.12.0
Requires-Dist: kuzu>=0.8.0
Requires-Dist: rank-bm25>=0.2.2
Requires-Dist: ollama>=0.4.0
Requires-Dist: llama-index>=0.12.0
Requires-Dist: llama-index-core>=0.12.0
Requires-Dist: pypdf>=5.1.0
Requires-Dist: python-docx>=1.1.0
Dynamic: license-file
Dynamic: requires-python
